Muskit/ComandMain.py
Muskit/QuantumGates.py
Muskit/__init__.py
Muskit/executorConfig.py
Muskit/functionalities.py
Muskit/generatorConfig.py
Muskit/graphicMain.py
Muskit/testCases.py
Muskit-0.0.3.dist-info/LICENSE
Muskit-0.0.3.dist-info/METADATA
Muskit-0.0.3.dist-info/WHEEL
Muskit-0.0.3.dist-info/top_level.txt
Muskit-0.0.3.dist-info/RECORD
