Metadata-Version: 2.1
Name: Muskit
Version: 0.0.3
Summary: Quantum mutant generator framework
Home-page: https://github.com/EnautMendi/QuantumMutationQiskit
Author: Enaut Mendiluze Usandizaga
Author-email: enaut@simula.no
License: UNKNOWN
Platform: UNKNOWN
Classifier: Programming Language :: Python :: 3
Requires-Python: >=3.6
License-File: LICENSE
